microcosm_connexion/__init__.py
microcosm_connexion/error_handler.py
microcosm_connexion/factories.py
microcosm_connexion/resolver.py
microcosm_connexion-1.0.0.dist-info/METADATA
microcosm_connexion-1.0.0.dist-info/WHEEL
microcosm_connexion-1.0.0.dist-info/entry_points.txt
microcosm_connexion-1.0.0.dist-info/top_level.txt
microcosm_connexion-1.0.0.dist-info/RECORD
