Metadata-Version: 2.1
Name: microcosm-connexion
Version: 1.0.0
Summary: A python library that exposes microcosm factories for connexions
Home-page: https://github.com/srikalyan/microcosm-connexion
Author: Srikalyan Swayampakula
Author-email: 
License: UNKNOWN
Platform: UNKNOWN
Requires-Dist: connexion[swagger-ui] (<3,>=2.4.0)
Requires-Dist: inflection (<1,>=0.3.1)
Requires-Dist: microcosm (<3,>=2)
Requires-Dist: microcosm-flask (<3,>=2.2.0)
Requires-Dist: microcosm-logging (<2.0.0,>=1.6.0)
Provides-Extra: postgres
Requires-Dist: microcosm-postgres (<2.0.0,>=1.17.0) ; extra == 'postgres'
